{
  "asset_id": "hero-backgrounds_dark-sci-fi_veil-of-static_v8m3x2",
  "title": "Veil of Static",
  "category": "hero-backgrounds",
  "file_name": "hero-backgrounds_dark-sci-fi_veil-of-static_20260526T003000Z_v8m3x2.jpg",
  "relative_path": "approved-assets/hero-backgrounds/hero-backgrounds_dark-sci-fi_veil-of-static_20260526T003000Z_v8m3x2.jpg",
  "emotional_category": "dark-sci-fi",
  "genre": "Dark Sci-Fi",
  "creator_identity": "Movianx Originals",
  "atmospheric_profile": "atmospheric, mysterious, volumetric light shafts, vast orbital scale, contemplative isolation, deep space debris field with Earth crescent",
  "recommendation_tags": [
    "sci-fi",
    "space",
    "atmospheric",
    "isolation",
    "volumetric",
    "contemplative",
    "derelict"
  ],
  "rail_assignment": "featured-home-hero",
  "aspect_ratio": "16:9",
  "resolution": "cinematic-backdrop",
  "approved_at": "2026-05-26T00:32:00Z",
  "quality_notes": "Outstanding cinematic quality. Perfect embodiment of dark sci-fi emotional profile. Volumetric lighting, scale, and quiet mystery are premium. No artifacts, realistic suit and station details, evocative composition. Passes filter decisively.",
  "prompt_signature": "dark-sci-fi-orbital-station-astronaut-earth-crescent-volumetric-god-rays-debris-nebula-imax-70mm",
  "source_session": "session-019e61a9-9de8-7a52-a659-49ea331aa10c",
  "movianx_integration_notes": "Perfect for homepage hero background or large immersive rail. Strong world-building signal for sci-fi verticals."
}